[
{
  "name" : "Sea World San Diego",
  "description" : "Sea World San Diego is an animal theme park, oceanarium, outside aquarium, and marine mammal park, located in San Diego, California, United States. The park is owned by SeaWorld Entertainment.",
  "address" : "Mission Bay Park, 500 Sea World Dr, San Diego, CA 92109",
  "price" : [50, 70],
  "category" : "Attraction",
  "lat" : 32.764107,
  "longitude" : -117.226265,
  "marker" : null
},
{
  "name" : "Legoland",
  "description" : "Legoland California is a theme park, miniature park, and aquarium located in Carlsbad, California, based on the Lego toy brand.",
  "address" : "1 Legoland Dr, Carlsbad, CA 92008",
  "price" : [90, 100],
  "category" : "Attraction",
  "lat" : 33.126033,
  "longitude" : -117.312385,
  "marker" : null
},
{
  "name" : "San Diego Zoo",
  "description" : "",
  "address" : "",
  "price" : [40, 50],
  "category" : "Attraction",
  "lat" : 32.734589,
  "longitude" : -117.149120,
  "marker" : null
},
{
  "name" : "San Diego Zoo Safari Park",
  "description" : "",
  "address" : "",
  "price" : [40, 50],
  "category" : "Attraction",
  "lat" : 33.097470,
  "longitude" : -117.000201,
  "marker" : null
},
{
  "name" : "Aquatica San Diego",
  "description" : "",
  "address" : "",
  "price" : [40, 50],
  "category" : "Attraction",
  "lat" : 32.587630,
  "longitude" : -117.010759,
  "marker" : null
},
{
  "name" : "Birch Aquarium",
  "description" : "",
  "address" : "",
  "price" : [10, 20],
  "category" : "Attraction",
  "lat" : 32.8678,
  "longitude" : -117.2496,
  "marker" : null
},
{
  "name" : "La Jolla Shores",
  "description" : "",
  "address" : "",
  "price" : [0, 0],
  "category" : "Beach",
  "lat" : 32.856787,
  "longitude" : -117.256362,
  "marker" : null
},
{
  "name" : "Black's Beach",
  "description" : "",
  "address" : "",
  "price" : [0, 0],
  "category" : "Beach",
  "lat" : 32.889884,
  "longitude" : -117.251194,
  "marker" : null
},
{
  "name" : "Torrey Pines State Beach",
  "description" : "",
  "address" : "",
  "price" : [0, 0],
  "category" : "Beach",
  "lat" : 32.933677,
  "longitude" : -117.260678,
  "marker" : null
},
{
  "name" : "La Jolla Cove",
  "description" : "",
  "address" : "",
  "price" : [0, 0],
  "category" : "Beach",
  "lat" : 32.849680,
  "longitude" : -117.274679,
  "marker" : null
},
{
  "name" : "Solana Beach",
  "description" : "",
  "address" : "",
  "price" : [0, 0],
  "category" : "Beach",
  "lat" : 32.986230,
  "longitude" : -117.271689,
  "marker" : null
},
{
  "name" : "Coronado Beach",
  "description" : "",
  "address" : "",
  "price" : [0, 0],
  "category" : "Beach",
  "lat" : 32.684183,
  "longitude" : -117.184432,
  "marker" : null
},
{
  "name" : "Pacific Beach",
  "description" : "",
  "address" : "",
  "price" : [0, 0],
  "category" : "Beach",
  "lat" : 32.796561,
  "longitude" : -117.255475,
  "marker" : null
},
{
  "name" : "Mission Beach",
  "description" : "",
  "address" : "",
  "price" : [0, 0],
  "category" : "Beach",
  "lat" : 32.792095,
  "longitude" : -117.232337,
  "marker" : null
},
{
  "name" : "UCSD",
  "description" : "The University of California, San Diego is a public 
  research university located in the La Jolla 
  neighborhood of San Diego, California, 
  in the United States.",
  "address" : "9500 Gilman Drive, La Jolla, CA, 92093",
  "price" : [0, 0],
  "category" : "College Campus",
  "lat" : 32.877492,
  "longitude" : -117.235277,
  "marker" : null
},
{
  "name" : "SDSU",
  "description" : "San Diego State University is a public research university in San Diego, California, and is the largest and oldest higher education institution in San Diego County.",
  "address" : "5500 Campanile Dr, San Diego, CA 92182",
  "price" : [0, 0],
  "category" : "College Campus",
  "lat" : 32.774731,
  "longitude" : -117.069387,
  "marker" : null
},
{
  "name" : "USD",
  "description" : "The University of San Diego is a private Roman Catholic university in San Diego, California, United States. The university offers 42 baccalaureate degrees, and several degrees in law, nursing, and other doctorate programs.",
  "address" : "5998 Alcala Park, San Diego, CA 92110",
  "price" : [0, 0],
  "category" : "College Campus",
  "lat" : 32.770782,
  "longitude" : -117.192115,
  "marker" : null
},
{
  "name" : "San Diego City College",
  "description" : "San Diego City College is a public, two-year
   community college located in San Diego,
   California. City College is part of the San 
  Diego Community College District along with 
  San Diego Mesa College",
  "address" : "1313 Park Blvd, San Diego, CA 92101",
  "price" : [0, 0],
  "category" : "College Campus",
  "lat" : 32.722042,
  "longitude" : -117.153451,
  "marker" : null
},
{
  "name" : "National University",
  "description" : "National University is a private, nonprofit
  institution of higher education in California.
  Founded in 1971, National University is 
  headquartered in La Jolla, California, United 
  States.",
  "address" : "9388 Lightwave Ave, San Diego, CA 92123",
  "price" : [0, 0],
  "category" : "College Campus",
  "lat" : 32.829303,
  "longitude" : -117.127357,
  "marker" : null
},
{
  "name" : "San Diego Mesa College",
  "description" : "San Diego Mesa College is a public, two year community college located in the community of Clairemont Mesa in the City of San Diego, California in the United States.",
  "address" : "7250 Mesa College Dr, San Diego, CA 92111",
  "price" : [0, 0],
  "category" : "College Campus",
  "lat" : 32.803875,
  "longitude" : -117.163515,
  "marker" : null
},
{
  "name" : "Ashford University",
  "description" : "Ashford University is an online for-profit 
  university headquartered in San Diego, 
  California. It is the largest educational holding 
  of Bridgepoint Education.",
  "address" : "8620 Spectrum Center Blvd, San Diego, CA 92123",
  "price" : [0, 0],
  "category" : "College Campus",
  "lat" : 32.827258,
  "longitude" : -117.142030,
  "marker" : null
},
{
  "name" : "Point Loma Nazarene University",
  "description" : "Point Loma Nazarene University is a Christian 
  liberal arts college. Its main campus is located 
  on the Point Loma oceanfront in San Diego, 
  California, United States. It was founded in 1902
  as a Bible college by the Church of the 
  Nazarene.",
  "address" : "3900 Lomaland Dr, San Diego, CA 92106",
  "price" : [0, 0],
  "category" : "College Campus",
  "lat" : 32.718312,
  "longitude" : -117.250250,
  "marker" : null
},
{
  "name" : "Cabrillo National Monument",
  "description" : "Cabrillo National Monument is at the southern tip of the Point Loma Peninsula in San Diego, California. It commemorates the landing of Juan Rodríguez Cabrillo at San Diego Bay on September 28, 1542.",
  "address" : "1800 Cabrillo Memorial Dr, San Diego, CA 92106",
  "price" : [0, 0],
  "category" : "Landmark",
  "lat" : 32.673500,
  "longitude" : -117.242500,
  "marker" : null
},
{
  "name" : "Fort Rosecrans Cemetery",
  "description" : "Fort Rosecrans National Cemetery is a federal 
  military cemetery in the city of San Diego,
  California.",
  "address" : "1800 Cabrillo Memorial Dr, San Diego, CA 92106",
  "price" : [0, 0],
  "category" : "Landmark",
  "lat" : 32.688800,
  "longitude" : -117.244300,
  "marker" : null
},
{
  "name" : "Mount Soledad",
  "description" : "Mount Soledad is a prominent landmark in the 
  city of San Diego, California, United States. 
  The mountaintop is the site of the Mount 
  Soledad cross",
  "address" : "USGS La Jolla OE W",
  "price" : [0, 0],
  "category" : "Landmark",
  "lat" : 32.839800,
  "longitude" : -117.252300,
  "marker" : null
},
{
  "name" : "Coronado Bridge",
  "description" : "The San Diego–Coronado Bridge, locally
  referred to as the Coronado Bridge, is a 
  prestressed concrete/steel girder bridge, 
  crossing over San Diego Bay in the United 
  States, linking San Diego with Coronado, 
  California.",
  "address" : "Route 75 Coronado, San Diego, CA 92118",
  "price" : [0, 0],
  "category" : "Landmark",
  "lat" : 32.689400,
  "longitude" : -117.153400,
  "marker" : null
},
{
  "name" : "Point Loma Lighthouse",
  "description" : "The original Point Loma Lighthouse is a historic 
  lighthouse located on the Point Loma peninsula 
  at the mouth of San Diego Bay",
  "address" : "NSC San Diego, Point Loma Annex, 1800 Cabrillo
  Memorial Dr, San Diego, CA 92106",
  "price" : [0, 0],
  "category" : "Landmark",
  "lat" : 32.672000,
  "longitude" : -117.241000,
  "marker" : null
},
{
  "name" : "Embracing Peace Statue",
  "description" : "If the photograph of raising the American flag on 
  Iwo Jima is the quintessential World War II icon
  for triumph in a just war, then 'Unconditional 
  Surrender' is the icon for the just rewards of victory.",
  "address" : "55 Tuna Ln, San Diego, CA 92132",
  "price" : [0, 0],
  "category" : "Landmark",
  "lat" : 32.712900,
  "longitude" : -117.175200,
  "marker" : null
},
{
  "name" : "Torrey Pines Gliderport",
  "description" : "The Torrey Pines Gliderport is a city-owned private-use glider airport located in La Jolla",
  "address" : "2800 Torrey Pines Scenic Dr, La Jolla, CA 92037",
  "price" : [0, 0],
  "category" : "Landmark",
  "lat" : 32.889900,
  "longitude" : -117.251200,
  "marker" : null
},
{
  "name" : "Mormon Battalion Historic Site",
  "description" : "This newly remodeled center evokes 
  Old San Diego and includes hands-on 
  exhibits and resources for learning more 
  about those who served in the Battalion.",
  "address" : "2510 Juan St, San Diego, CA 92110",
  "price" : [0, 0],
  "category" : "Landmark",
  "lat" : 32.754200,
  "longitude" : -117.194200,
  "marker" : null
},
{
  "name" : "Mission Basilica San Diego de Alcala",
  "description" : "Visitors can explore the grounds of this 18th-century, still-active mission, the state's first.",
  "address" : "10818 San Diego Mission Rd, San Diego, CA 92108",
  "price" : [0, 0],
  "category" : "Landmark",
  "lat" : 32.784600,
  "longitude" : -117.106000,
  "marker" : null
},
{
  "name" : "National Salute to Bob Hope and the Military",
  "description" : "On the plaza, there are 15 life-sized bronze statues, arranged as if attending a Bob Hope show. Each figure represents a serviceman from a different conflict.",
  "address" : "Navy Pier, San Diego, CA 92132",
  "price" : [0, 0],
  "category" : "Landmark",
  "lat" : 32.712700,
  "longitude" : -117.175500,
  "marker" : null
},
{
  "name" : "San Diego California Temple",
  "description" : "The San Diego California Temple is the 47th 
  constructed and 45th operating temple of The 
  Church of Jesus Christ of Latter-day Saints.",
  "address" : "7474 Charmant Dr, San Diego, CA 92122",
  "price" : [0, 0],
  "category" : "Landmark",
  "lat" : 32.866400,
  "longitude" : -117.228800,
  "marker" : null
},
{
  "name" : "Salk Institute for Biological Studies",
  "description" : "The Salk Institute for Biological Studies is an independent, non-profit, scientific research institute located in La Jolla, San Diego, California, United States.",
  "address" : "10010 N Torrey Pines Rd, La Jolla, CA 92037",
  "price" : [0, 0],
  "category" : "Landmark",
  "lat" : 32.887151,
  "longitude" : -117.246212,
  "marker" : null
},

]
